{
  "resources":{
  "includes":[
    {"pattern":"\\Qbabashka_example/core.cljc\\E"}, 
    {"pattern":"\\Qbabashka_example/core__init.class\\E"}, 
    {"pattern":"\\Qclojure/core.clj\\E"}, 
    {"pattern":"\\Qclojure/core/protocols.clj\\E"}, 
    {"pattern":"\\Qclojure/core/protocols__init.class\\E"}, 
    {"pattern":"\\Qclojure/core/server.clj\\E"}, 
    {"pattern":"\\Qclojure/core/server__init.class\\E"}, 
    {"pattern":"\\Qclojure/core__init.class\\E"}, 
    {"pattern":"\\Qclojure/core_deftype.clj\\E"}, 
    {"pattern":"\\Qclojure/core_deftype__init.class\\E"}, 
    {"pattern":"\\Qclojure/core_print.clj\\E"}, 
    {"pattern":"\\Qclojure/core_print__init.class\\E"}, 
    {"pattern":"\\Qclojure/core_proxy.clj\\E"}, 
    {"pattern":"\\Qclojure/core_proxy__init.class\\E"}, 
    {"pattern":"\\Qclojure/edn.clj\\E"}, 
    {"pattern":"\\Qclojure/edn__init.class\\E"}, 
    {"pattern":"\\Qclojure/genclass.clj\\E"}, 
    {"pattern":"\\Qclojure/genclass__init.class\\E"}, 
    {"pattern":"\\Qclojure/gvec.clj\\E"}, 
    {"pattern":"\\Qclojure/gvec__init.class\\E"}, 
    {"pattern":"\\Qclojure/instant.clj\\E"}, 
    {"pattern":"\\Qclojure/instant__init.class\\E"}, 
    {"pattern":"\\Qclojure/java/io.clj\\E"}, 
    {"pattern":"\\Qclojure/java/io__init.class\\E"}, 
    {"pattern":"\\Qclojure/main.clj\\E"}, 
    {"pattern":"\\Qclojure/main__init.class\\E"}, 
    {"pattern":"\\Qclojure/spec/alpha.clj\\E"}, 
    {"pattern":"\\Qclojure/spec/alpha__init.class\\E"}, 
    {"pattern":"\\Qclojure/spec/gen/alpha.clj\\E"}, 
    {"pattern":"\\Qclojure/spec/gen/alpha__init.class\\E"}, 
    {"pattern":"\\Qclojure/string.clj\\E"}, 
    {"pattern":"\\Qclojure/string__init.class\\E"}, 
    {"pattern":"\\Qclojure/uuid.clj\\E"}, 
    {"pattern":"\\Qclojure/uuid__init.class\\E"}, 
    {"pattern":"\\Qclojure/version.properties\\E"}, 
    {"pattern":"\\Qclojure/walk.clj\\E"}, 
    {"pattern":"\\Qclojure/walk__init.class\\E"}, 
    {"pattern":"\\Qfierycod/holy_lambda/agent.clj\\E"}, 
    {"pattern":"\\Qfierycod/holy_lambda/agent__init.class\\E"}, 
    {"pattern":"\\Qfierycod/holy_lambda/core.cljc\\E"}, 
    {"pattern":"\\Qfierycod/holy_lambda/core__init.class\\E"}, 
    {"pattern":"\\Qfierycod/holy_lambda/interceptor.cljc\\E"}, 
    {"pattern":"\\Qfierycod/holy_lambda/interceptor__init.class\\E"}, 
    {"pattern":"\\Qfierycod/holy_lambda/java_runtime.clj\\E"}, 
    {"pattern":"\\Qfierycod/holy_lambda/java_runtime__init.class\\E"}, 
    {"pattern":"\\Qfierycod/holy_lambda/native_runtime.clj\\E"}, 
    {"pattern":"\\Qfierycod/holy_lambda/native_runtime__init.class\\E"}, 
    {"pattern":"\\Qfierycod/holy_lambda/response.clj\\E"}, 
    {"pattern":"\\Qfierycod/holy_lambda/response__init.class\\E"}, 
    {"pattern":"\\Qfierycod/holy_lambda/retriever.clj\\E"}, 
    {"pattern":"\\Qfierycod/holy_lambda/retriever__init.class\\E"}, 
    {"pattern":"\\Qfierycod/holy_lambda/util.cljc\\E"}, 
    {"pattern":"\\Qfierycod/holy_lambda/util__init.class\\E"}, 
    {"pattern":"\\Qjsonista/core.clj\\E"}, 
    {"pattern":"\\Qjsonista/core__init.class\\E"}
  ]},
  "bundles":[]
}
